mehdashti_encryption/__init__.py
mehdashti_encryption/py.typed
mehdashti_encryption/service.py
mehdashti_encryption-0.2.0.dist-info/METADATA
mehdashti_encryption-0.2.0.dist-info/WHEEL
mehdashti_encryption-0.2.0.dist-info/RECORD
