Metadata-Version: 2.4
Name: mehdashti-encryption
Version: 0.2.0
Summary: AES-256-GCM encryption with key rotation and context binding support
Project-URL: Homepage, https://github.com/mehdashti/smart-platform
Project-URL: Repository, https://github.com/mehdashti/smart-platform.git
Project-URL: Issues, https://github.com/mehdashti/smart-platform/issues
Author-email: Mahdi Ashti <mahdi@mehdashti.com>
License: MIT
Keywords: aes-gcm,encryption,key-rotation,security
Classifier: Development Status :: 4 - Beta
Classifier: Intended Audience :: Developers
Classifier: License :: OSI Approved :: MIT License
Classifier: Programming Language :: Python :: 3
Classifier: Programming Language :: Python :: 3.13
Classifier: Topic :: Security :: Cryptography
Requires-Python: >=3.13
Requires-Dist: cryptography>=44.0.0
Provides-Extra: dev
Requires-Dist: pytest>=8.0.0; extra == 'dev'
Requires-Dist: ruff>=0.8.0; extra == 'dev'
